shadebags/__init__.py
shadebags/abc_decoder.py
shadebags/abc_encoder.py
shadebags/defaults.py
shadebags/reader.py
shadebags/shade_msg.py
shadebags/utils.py
shadebags/writer.py
shadebags/compression/__init__.py
shadebags/compression/compressor.py
shadebags/compression/image_formats.py
shadebags/compression/pointcloud.py
shadebags/ros1/__init__.py
shadebags/ros1/decoder.py
shadebags/ros1/encoder.py
shadebags/ros1/type_converter.py
shadebags-1.0.0b0.dist-info/LICENSE
shadebags-1.0.0b0.dist-info/METADATA
shadebags-1.0.0b0.dist-info/WHEEL
shadebags-1.0.0b0.dist-info/entry_points.txt
shadebags-1.0.0b0.dist-info/top_level.txt
shadebags-1.0.0b0.dist-info/RECORD
