Metadata-Version: 2.1
Name: shadebags
Version: 1.0.0b0
Summary: Quickly compress & share indexed rosbags
Home-page: https://github.com/open-shade/shadebags
Author: Emerson Dove
Author-email: emerson+github@shade.inc
License: lgpl-2.1
Keywords: Robotics,Ros,Compression
Classifier: Development Status :: 4 - Beta
Classifier: Intended Audience :: Developers
Classifier: License :: OSI Approved :: GNU Lesser General Public License v2 or later (LGPLv2+)
Classifier: Programming Language :: Python :: 3.8
Classifier: Programming Language :: Python :: 3.9
Classifier: Programming Language :: Python :: 3.10
License-File: LICENSE
Requires-Dist: pillow
Requires-Dist: tqdm
